alexa_webcrawler/__init__.py
alexa_webcrawler/main.py
alexa_webcrawler-0.1.0.dist-info/entry_points.txt
alexa_webcrawler-0.1.0.dist-info/WHEEL
alexa_webcrawler-0.1.0.dist-info/METADATA
alexa_webcrawler-0.1.0.dist-info/RECORD
